LICENSE
LICENSE.txt
MANIFEST.in
README.md
requirements.txt
setup.cfg
setup.py
ciscomeapi/__init__.py
ciscomeapi/_me_api.py
ciscomeapi/ciscomeapi.py
ciscomeapi/exceptions.py
ciscomeapi/function_templates.py
ciscomeapi/gen-endpoints.py
ciscomeapi/helpers.py
ciscomeapi.egg-info/PKG-INFO
ciscomeapi.egg-info/SOURCES.txt
ciscomeapi.egg-info/dependency_links.txt
ciscomeapi.egg-info/not-zip-safe
ciscomeapi.egg-info/requires.txt
ciscomeapi.egg-info/top_level.txt
docs/history.rst
docs/readme.rst