Metadata-Version: 2.1
Name: ciscomeapi
Version: 0.5
Summary: An unofficial Cisco Mobility Express Python API.
Home-page: https://github.com/anuzellig/ciscomeapi
Author: Greg Anuzelli
Author-email: anuzellig@gmail.com
License: MIT license
Download-URL: https://github.com/anuzellig/ciscomeapi/archive/v_05.tar.gz
Keywords: cisco,wireless
Platform: UNKNOWN
Classifier: Development Status :: 4 - Beta
Classifier: Intended Audience :: Developers
Classifier: License :: OSI Approved :: MIT License
Classifier: Natural Language :: English
Classifier: Programming Language :: Python :: 3.5
License-File: LICENSE
License-File: LICENSE.txt
